LICENSE
MANIFEST.in
README.md
pavement.py
setup.py
bigdata/__init__.py
bigdata/bd.py
bigdata.egg-info/PKG-INFO
bigdata.egg-info/SOURCES.txt
bigdata.egg-info/dependency_links.txt
bigdata.egg-info/not-zip-safe
bigdata.egg-info/top_level.txt