Metadata-Version: 1.1
Name: bigdata
Version: 0.0.0
Summary: IPython magic for running Apache tools for Big Data
Home-page: http://github.com/jdvelasq/ipython-big-data
Author: Juan D. Velasquez
Author-email: jdvelasq@unal.edu.co
License: MIT
Keywords: big-data database ipython jupyter hadoop pig hive drill
Platform: UNKNOWN
Classifier: Development Status :: 3 - Alpha
Classifier: Environment :: Console
Classifier: Topic :: Database
Classifier: Topic :: Database :: Front-Ends
Classifier: License :: OSI Approved :: MIT License
Classifier: Programming Language :: Python :: 3.5
